temporalcache/__init__.py
temporalcache/expire.py
temporalcache/interval.py
temporalcache/persistent_lru_cache.py
temporalcache/utils.py
temporalcache/tests/__init__.py
temporalcache/tests/test_all.py
temporalcache/tests/test_expire.py
temporalcache/tests/test_interval.py
temporalcache/tests/test_persistent.py
temporalcache/tests/test_utils.py
temporal_cache-0.1.6.dist-info/METADATA
temporal_cache-0.1.6.dist-info/WHEEL
temporal_cache-0.1.6.dist-info/licenses/LICENSE
temporal_cache-0.1.6.dist-info/RECORD
