Metadata-Version: 2.4
Name: temporal-cache
Version: 0.1.6
Summary: Time based function caching
Project-URL: Repository, https://github.com/timkpaine/temporal-cache
Project-URL: Homepage, https://github.com/timkpaine/temporal-cache
Author-email: the temporal-cache authors <3105306+timkpaine@users.noreply.github.com>
License: Apache-2.0
License-File: LICENSE
Classifier: Development Status :: 3 - Alpha
Classifier: Programming Language :: Python
Classifier: Programming Language :: Python :: 3
Classifier: Programming Language :: Python :: 3.9
Classifier: Programming Language :: Python :: 3.10
Classifier: Programming Language :: Python :: 3.11
Classifier: Programming Language :: Python :: 3.12
Classifier: Programming Language :: Python :: Implementation :: CPython
Classifier: Programming Language :: Python :: Implementation :: PyPy
Requires-Python: >=3.9
Requires-Dist: frozendict>=1.2
Requires-Dist: pytz
Requires-Dist: tzlocal>=2.0.0
Provides-Extra: develop
Requires-Dist: build; extra == 'develop'
Requires-Dist: bump-my-version; extra == 'develop'
Requires-Dist: check-manifest; extra == 'develop'
Requires-Dist: hatchling; extra == 'develop'
Requires-Dist: pytest; extra == 'develop'
Requires-Dist: pytest-cov; extra == 'develop'
Requires-Dist: ruff; extra == 'develop'
Requires-Dist: twine; extra == 'develop'
Requires-Dist: wheel; extra == 'develop'
